selenium_oxide/__init__.py
selenium_oxide/exploit_builder.py
selenium_oxide/user_generator.py
selenium_oxide-1.2.1.dist-info/METADATA
selenium_oxide-1.2.1.dist-info/WHEEL
selenium_oxide-1.2.1.dist-info/top_level.txt
selenium_oxide-1.2.1.dist-info/RECORD
