Metadata-Version: 2.1
Name: selenium-oxide
Version: 1.2.1
Summary: A Selenium boilerplate for automating web exploits. Use responsibly and ethically.
Home-page: https://github.com/ApprenticeofEnder/Selenium-Oxide
Download-URL: https://github.com/ApprenticeofEnder/Selenium-Oxide
Author: Robert Babaev
Author-email: mail@robertbabaev.tech
License: MIT License
Keywords: Selenium,Web,Offensive Security
Requires-Dist: selenium (~=4.1.3)
Requires-Dist: Faker (~=13.15.1)
Requires-Dist: requests (~=2.28.1)
